llmfast/Chatbot.py
llmfast/__init__.py
llmfast-0.0.2.dist-info/LICENSE
llmfast-0.0.2.dist-info/METADATA
llmfast-0.0.2.dist-info/WHEEL
llmfast-0.0.2.dist-info/top_level.txt
llmfast-0.0.2.dist-info/RECORD
