Metadata-Version: 2.1
Name: llmfast
Version: 0.0.2
Summary: It's a Python LLM package
Home-page: https://github.com/Abdul-Jaweed/llmfast
Author: Abdul-Jaweed
Author-email: jdgaming7320@gmail.com
License: MIT
Project-URL: Bug Tracker, https://github.com/Abdul-Jaweed/llmfast/issues
Classifier: Programming Language :: Python :: 3.9
Classifier: Programming Language :: Python :: 3.10
Classifier: Programming Language :: Python :: 3.11
Classifier: Operating System :: OS Independent
Requires-Python: >=3.9
License-File: LICENSE
Requires-Dist: ensure ==1.0.2
Provides-Extra: testing
Requires-Dist: pytest >=7.1.3 ; extra == 'testing'
Requires-Dist: mypy >=0.971 ; extra == 'testing'
Requires-Dist: flake8 >=5.0.4 ; extra == 'testing'
Requires-Dist: tox >=3.25.1 ; extra == 'testing'
Requires-Dist: black >=22.8.0 ; extra == 'testing'
